libsql_graph_db/__init__.py
libsql_graph_db/database.py
libsql_graph_db/embeddings.py
libsql_graph_db/graph.py
libsql_graph_db/ml.py
libsql_graph_db/models.py
libsql_graph_db/natural.py
libsql_graph_db/sql/delete-edge-embedding.sql
libsql_graph_db/sql/delete-edge.sql
libsql_graph_db/sql/delete-node-embedding.sql
libsql_graph_db/sql/delete-node.sql
libsql_graph_db/sql/existing-edge.sql
libsql_graph_db/sql/existing-node.sql
libsql_graph_db/sql/insert-edge-embedding.sql
libsql_graph_db/sql/insert-edge.sql
libsql_graph_db/sql/insert-node-embedding.sql
libsql_graph_db/sql/insert-node.sql
libsql_graph_db/sql/schema.sql
libsql_graph_db/sql/search-edges-inbound.sql
libsql_graph_db/sql/search-edges-outbound.sql
libsql_graph_db/sql/search-edges.sql
libsql_graph_db/sql/search-node.template
libsql_graph_db/sql/search-where.template
libsql_graph_db/sql/traverse.template
libsql_graph_db/sql/update-node.sql
libsql_graph_db/sql/vector-search-edge.sql
libsql_graph_db/sql/vector-search-node.sql
libsql_graph_db/tests/__init__.py
libsql_graph_db/tests/conftest.py
libsql_graph_db/tests/test_database.py
libsql_graph_db/tests/test_graph.py
libsql_graph_db/tests/test_ml.py
libsql_graph_db/tests/test_natural.py
libsql_graph_db/tests/test_visualizers.py
libsql_graph_db/visualizers.py
libsql_graph_db-0.1.3.dist-info/LICENSE
libsql_graph_db-0.1.3.dist-info/METADATA
libsql_graph_db-0.1.3.dist-info/WHEEL
libsql_graph_db-0.1.3.dist-info/RECORD
