Metadata-Version: 2.1
Name: libsql-graph-db
Version: 0.1.3
Summary: Graph database in LibSQL
License: MIT
Author: Anubhuti Bhardwaj
Author-email: anubhutibhardwaj11@gmail.com
Requires-Python: >=3.11,<4.0
Classifier: License :: OSI Approved :: MIT License
Classifier: Programming Language :: Python :: 3
Classifier: Programming Language :: Python :: 3.11
Classifier: Programming Language :: Python :: 3.12
Requires-Dist: fastapi (>=0.110.0,<0.111.0)
Requires-Dist: graphviz (>=0.20.1,<0.21.0)
Requires-Dist: instructor (>=0.6.7,<0.7.0)
Requires-Dist: jinja2 (>=3.1.3,<4.0.0)
Requires-Dist: libsql-experimental (>=0.0.28,<0.0.29)
Requires-Dist: openai (>=1.14.2,<2.0.0)
Requires-Dist: pytest (>=8.1.1,<9.0.0)
Requires-Dist: pytest-mock (>=3.14.0,<4.0.0)
Requires-Dist: python-dotenv (>=1.0.1,<2.0.0)
Requires-Dist: sqlite-vss (>=0.1.2,<0.2.0)
Requires-Dist: uvicorn (>=0.29.0,<0.30.0)
